TemplatedData/__init__.py
TemplatedData/__version__.py
robotframework_templateddata-1.4.0.dist-info/LICENSE
robotframework_templateddata-1.4.0.dist-info/METADATA
robotframework_templateddata-1.4.0.dist-info/WHEEL
robotframework_templateddata-1.4.0.dist-info/top_level.txt
robotframework_templateddata-1.4.0.dist-info/RECORD
