Metadata-Version: 2.1
Name: robotframework-templateddata
Version: 1.4.0
Summary: Robot Framework library for generating test data from templates
Home-page: https://github.com/bhirsz/robotframework-templateddata
Author: Bartlomiej Hirsz
Author-email: bartek.hirsz@gmail.com
License: Apache License 2.0
Platform: any
Classifier: License :: OSI Approved :: Apache Software License
Classifier: Operating System :: OS Independent
Classifier: Programming Language :: Python :: 3.6
Classifier: Programming Language :: Python :: 3.7
Classifier: Programming Language :: Python :: 3.8
Classifier: Framework :: Robot Framework :: Tool
Classifier: Topic :: Software Development :: Quality Assurance
Classifier: Topic :: Utilities
License-File: LICENSE
Requires-Dist: robotframework (>=3.2.1)
Requires-Dist: jinja2
